{"version": "https://jsonfeed.org/version/1", "title": "Kuru Rent Website", "home_page_url": "https://kuru.rent/", "feed_url": "https://kuru.rent/feed_json_created.json", "description": "Kuru Rent adalah platform penyewaan kostum cosplay, hijab, dan wig yang berlokasi di Bandung. Kami menyediakan berbagai macam kostum cosplay, hijab, dan wig yang bisa disewa untuk keperluan acara, photoshoot, dan lainnya. Kuru Rent juga menyediakan jasa pembuatan kostum cosplay, hijab, dan wig sesuai dengan keinginan anda.", "icon": null, "authors": [], "language": "id", "items": []}